FuPy/__init__.py
FuPy/all.py
FuPy/basics.py
FuPy/core.py
FuPy/fixpoints.py
FuPy/laziness.py
FuPy/operator_.py
FuPy/prelude.py
FuPy/tracing.py
FuPy/tracing_basics.py
FuPy/tracing_laziness.py
FuPy/utils.py
fupy-0.9.1.dist-info/licenses/LICENSE.txt
fupy-0.9.1.dist-info/METADATA
fupy-0.9.1.dist-info/WHEEL
fupy-0.9.1.dist-info/top_level.txt
fupy-0.9.1.dist-info/RECORD
