Metadata-Version: 2.4
Name: FuPy
Version: 0.9.1
Summary: Functional Programming in Python, for Education
Author-email: "Tom Verhoeff (Eindhoven Univesity of Technology)" <T.Verhoeff@tue.nl>
License: MIT License
Project-URL: Homepage, https://gitlab.tue.nl/t-verhoeff-software/FuPy
Project-URL: Documentation, https://fupy.readthedocs.io/
Project-URL: Source, https://gitlab.tue.nl/t-verhoeff-software/FuPy/
Project-URL: Issues, https://gitlab.tue.nl/t-verhoeff-software/fupy/-/issues
Keywords: functional programming,education
Classifier: Development Status :: 3 - Alpha
Classifier: Intended Audience :: Education
Classifier: Intended Audience :: Science/Research
Classifier: Topic :: Software Development :: Interpreters
Classifier: Topic :: Software Development :: Code Generators
Classifier: License :: OSI Approved :: MIT License
Classifier: Programming Language :: Python :: 3
Classifier: Programming Language :: Python :: 3.12
Classifier: Operating System :: OS Independent
Requires-Python: >=3.12
License-File: LICENSE.txt
Provides-Extra: testing
Requires-Dist: pytest>=6.0; extra == "testing"
Requires-Dist: pytest-mock>=3.5; extra == "testing"
Requires-Dist: pytest-cov>=2.12; extra == "testing"
Provides-Extra: docs
Requires-Dist: sphinx>=4.0; extra == "docs"
Requires-Dist: sphinx-rtd-theme>=1.0; extra == "docs"
Requires-Dist: recommonmark>=0.7; extra == "docs"
Requires-Dist: myst_parser>=3.0; extra == "docs"
Dynamic: license-file
